{"is_source_file": true, "format": "JavaScript", "description": "This file exports a singleton function for creating and retrieving a configured Supabase client, with environment variable checks and support for mock mode. It includes methods for client initialization and comments about future OAuth integrations.", "external_files": ["@supabase/supabase-js"], "external_methods": ["createClient"], "published": ["getSupabaseClient"], "classes": [], "methods": [{"name": "getSupabaseClient()", "description": "Returns a singleton instance of the Supabase client, initializing it with environment variables if not already created.", "scope": "", "scopeKind": ""}], "calls": ["createClient"], "search-terms": ["Supabase client singleton", "React environment variables", "supabase-js", "createClient", "Supabase authentication"], "state": 2, "file_id": 30, "knowledge_revision": 66, "git_revision": "", "ctags": [{"_type": "tag", "name": "_client", "path": "/home/kavia/workspace/code-generation/weekly-insight-report-platform-22440-22608/web/src/lib/supabaseClient.js", "pattern": "/^let _client = null;$/", "language": "JavaScript", "kind": "variable"}, {"_type": "tag", "name": "getSupabaseClient", "path": "/home/kavia/workspace/code-generation/weekly-insight-report-platform-22440-22608/web/src/lib/supabaseClient.js", "pattern": "/^export function getSupabaseClient() {$/", "language": "JavaScript", "kind": "function", "signature": "()"}], "hash": "a04ef126eabaab6d1f93a0f819738248", "format-version": 4, "code-base-name": "web", "filename": "web/src/lib/supabaseClient.js", "fields": [{"name": "let _client = null;", "scope": "", "scopeKind": "", "description": "unavailable"}], "revision_history": [{"66": ""}]}