{"is_source_file": true, "format": "JavaScript", "description": "This file provides a singleton pattern for creating and retrieving a Supabase client instance. It handles both real and mock clients based on environment variables, allowing the application to operate even without proper configuration for testing or local development.", "external_files": ["@supabase/supabase-js"], "external_methods": ["createClient"], "published": ["getSupabaseClient", "default"], "classes": [], "methods": [{"name": "createMockClient()", "description": "Creates a lightweight mock Supabase client with stubbed methods to enable app functionality without a real backend.", "scope": "", "scopeKind": ""}, {"name": "getSupabaseClient()", "description": "Returns a singleton Supabase client instance, either real or mock, based on environment variables.", "scope": "", "scopeKind": ""}], "calls": ["createClient"], "search-terms": ["supabase", "createClient", "singleton", "mock client", "environment variables"], "state": 2, "file_id": 35, "knowledge_revision": 93, "git_revision": "", "ctags": [{"_type": "tag", "name": "client", "path": "/home/kavia/workspace/code-generation/weekly-insight-report-platform-22440-22608/web/src/lib/supabaseClient.js", "pattern": "/^let client = null;$/", "language": "JavaScript", "kind": "variable"}, {"_type": "tag", "name": "createMockClient", "path": "/home/kavia/workspace/code-generation/weekly-insight-report-platform-22440-22608/web/src/lib/supabaseClient.js", "pattern": "/^function createMockClient() {$/", "language": "JavaScript", "kind": "function", "signature": "()"}, {"_type": "tag", "name": "getSupabaseClient", "path": "/home/kavia/workspace/code-generation/weekly-insight-report-platform-22440-22608/web/src/lib/supabaseClient.js", "pattern": "/^export function getSupabaseClient() {$/", "language": "JavaScript", "kind": "function", "signature": "()"}], "hash": "ace55d7010eeae60b3865cd7d0df31a9", "format-version": 4, "code-base-name": "web", "filename": "web/src/lib/supabaseClient.js", "fields": [{"name": "let client = null;", "scope": "", "scopeKind": "", "description": "unavailable"}], "revision_history": [{"93": ""}]}